setup.py
Smart_Ventilator.egg-info/PKG-INFO
Smart_Ventilator.egg-info/SOURCES.txt
Smart_Ventilator.egg-info/dependency_links.txt
Smart_Ventilator.egg-info/top_level.txt
fanscript/__init__.py
fanscript/activate.py
fanscript/fan_script.py